BugMaker_Project_SDK/__init__.py
BugMaker_Project_SDK/a1z26.py
BugMaker_Project_SDK/bilibiliApi.py
BugMaker_Project_SDK/game.py
BugMaker_Project_SDK/search.py
BugMaker_Project_SDK/sort.py
BugMaker_Project_SDK-0.0.0.3.post6.dist-info/LICENSE
BugMaker_Project_SDK-0.0.0.3.post6.dist-info/METADATA
BugMaker_Project_SDK-0.0.0.3.post6.dist-info/WHEEL
BugMaker_Project_SDK-0.0.0.3.post6.dist-info/top_level.txt
BugMaker_Project_SDK-0.0.0.3.post6.dist-info/RECORD
